{
"places":[
    {
        "id": "place1",
        "cityName": "Oahu",
        "cityState": "Hawaii",
        "cityImage": "https://raw.githubusercontent.com/Lakiajo/Fav-Places/master/IMG_4970.JPG",
        "favoriteRestaurant": "Eggs N' Things",
        "favoriteBar": "Didn't Visit any",
        "favoriteHotel": "NA",
        "favoriteTouristAttraction": "Honolulu Museum of Art"
     },
     {
        "id": "place2",
        "cityName": "Norcross",
        "cityState": "Georgia",
        "cityImage": "http://www.highmarkconsult.com/wordpress/wp-content/uploads/2016/02/the-forum-1024x744@2x.jpg",
        "favoriteRestaurant": "Sugo",
        "favoriteBar": "Dominics",
        "favoriteHotel": "Hilton Atlanta Northeast",
        "favoriteTouristAttraction": "Mountains"
     },
     {
        "id": "place3",
        "cityName": "Austin",
        "cityState": "Texas",
        "cityImage": "https://i.ytimg.com/vi/5LCp_8C6hE0/maxresdefault.jpg",
        "favoriteRestaurant": "Rosa's Cafe",
        "favoriteBar": "All of them",
        "favoriteHotel": "NA",
        "favoriteTouristAttraction": "Barton Lake"
     },
     {
        "id": "place4",
        "cityName": "Los Angeles",
        "cityState": "California",
        "cityImage": "https://upload.wikimedia.org/wikipedia/commons/3/30/Echo_Park_Lake_with_Downtown_Los_Angeles_Skyline.jpg",
        "favoriteRestaurant": "Taco Taco",
        "favoriteBar": "BarNine",
        "favoriteHotel": "Any of them",
        "favoriteTouristAttraction": "Santa Monica Pier"
     },
     {
        "id": "Place5",
        "cityName": "Daytona",
        "cityState": "Florida",
        "cityImage": "https://www.tripsavvy.com/thmb/rbgKFSqjAfDFq5SsztjGnEQDAn8=/960x0/filters:no_upscale():max_bytes(150000):strip_icc()/beachfront-hotels-along-daytona-beach--148937038-597555950d327a00117eca49.jpg",
        "favoriteRestaurant": "All of em",
        "favoriteBar": "high",
        "favoriteHotel": "Hilton Oceanfront Daytona Beach",
        "favoriteTouristAttraction": "Daytona Beach"
     }

   ]
}
